sanghyunjo/__init__.py
sanghyunjo/ai.py
sanghyunjo/ai_utils.py
sanghyunjo/cv.py
sanghyunjo/cv_utils.py
sanghyunjo/json_utils.py
sanghyunjo/misc.py
sanghyunjo/xml_utils.py
sanghyunjo/fonts/Times New Roman MT Std.otf
sanghyunjo-1.8.1.data/data/fonts/Times New Roman MT Std.otf
sanghyunjo-1.8.1.dist-info/LICENSE
sanghyunjo-1.8.1.dist-info/METADATA
sanghyunjo-1.8.1.dist-info/WHEEL
sanghyunjo-1.8.1.dist-info/top_level.txt
sanghyunjo-1.8.1.dist-info/RECORD
