Metadata-Version: 2.1
Name: sanghyunjo
Version: 1.8.1
Summary: Wrapped utility functions for existing AI packages to simplify their usage
Home-page: https://github.com/shjo-april/sanghyunjo
Author: Sanghyun Jo (shjo-april)
Author-email: shjo.april@gmail.com
Keywords: sanghyun,sanghyunjo,shjo,ai,utils,wrapper
Requires-Python: >=3.8
License-File: LICENSE
Requires-Dist: joblib
Requires-Dist: cmapy
Requires-Dist: tqdm
Requires-Dist: opencv-python
Requires-Dist: Pillow
Requires-Dist: requests
